CHANGES.rst
CONTRIBUTORS.rst
MANIFEST.in
README.rst
VERSION
setup.cfg
setup.py
docs/LICENSE.GPL
docs/LICENSE.rst
docs/index.rst
src/visaplan/__init__.py
src/visaplan.plone.infohubs.egg-info/PKG-INFO
src/visaplan.plone.infohubs.egg-info/SOURCES.txt
src/visaplan.plone.infohubs.egg-info/dependency_links.txt
src/visaplan.plone.infohubs.egg-info/entry_points.txt
src/visaplan.plone.infohubs.egg-info/namespace_packages.txt
src/visaplan.plone.infohubs.egg-info/not-zip-safe
src/visaplan.plone.infohubs.egg-info/requires.txt
src/visaplan.plone.infohubs.egg-info/top_level.txt
src/visaplan/plone/__init__.py
src/visaplan/plone/infohubs/__init__.py
src/visaplan/plone/infohubs/configure.zcml
src/visaplan/plone/infohubs/hubs.py
src/visaplan/plone/infohubs/hubs.py.test
src/visaplan/plone/infohubs/hubs2.py
src/visaplan/plone/infohubs/utils.py
src/visaplan/plone/infohubs/browser/__init__.py
src/visaplan/plone/infohubs/browser/browser.py
src/visaplan/plone/infohubs/browser/configure.zcml
src/visaplan/plone/infohubs/browser/demo.py
src/visaplan/plone/infohubs/browser/interfaces.py
src/visaplan/plone/infohubs/browser/templates/infohubs-demo.pt