Metadata-Version: 2.1
Name: visaplan.plone.infohubs
Version: 1.2.0
Summary: A mini language for reuse of information
Home-page: UNKNOWN
Author: Tobias Herp
Author-email: tobias.herp@visaplan.com
License: GPL version 2
Project-URL: Source, https://github.com/visaplan/plone.infohubs
Project-URL: Documentation, https://pypi.org/project/visaplan.plone.infohubs
Project-URL: Tracker, https://github.com/visaplan/plone.infohubs/issues
Platform: UNKNOWN
Classifier: Environment :: Web Environment
Classifier: Framework :: Plone
Classifier: Framework :: Plone :: 4.3
Classifier: Framework :: Plone :: 5.0
Classifier: Framework :: Plone :: 5.1
Classifier: Framework :: Plone :: 5.2
Classifier: Framework :: Zope2
Classifier: Programming Language :: Python
Classifier: Programming Language :: Python :: 2.7
Classifier: Programming Language :: Python :: 3.3
Classifier: Programming Language :: Python :: 3.4
Classifier: Programming Language :: Python :: 3.5
Classifier: Programming Language :: Python :: 3.6
Classifier: Programming Language :: Python :: 3.7
Classifier: Intended Audience :: Developers
Classifier: Natural Language :: German
Classifier: Operating System :: OS Independent
Classifier: License :: OSI Approved :: GNU General Public License v2 (GPLv2)
